generalgui/__init__.py
generalgui/elements/__init__.py
generalgui/elements/button.py
generalgui/elements/checkbutton.py
generalgui/elements/entry.py
generalgui/elements/label.py
generalgui/elements/page.py
generalgui/elements/subelements/__init__.py
generalgui/elements/subelements/password.py
generalgui/pages/__init__.py
generalgui/pages/payment.py
generalgui/pages/plot.py
generalgui/pages/signin.py
generalgui/properties/__init__.py
generalgui/properties/contain.py
generalgui/properties/editable.py
generalgui/properties/funcs.py
generalgui/properties/generic.py
generalgui/properties/generic_app.py
generalgui/properties/generic_binder.py
generalgui/properties/generic_drawer.py
generalgui/properties/generic_indexer.py
generalgui/properties/generic_states.py
generalgui/properties/text.py
generalgui/properties/toggle.py
generalgui/test/__init__.py
generalgui/test/test_create.py
generalgui/test/test_draw.py
generalgui/test/test_generalgui.py
generalgui-2.0.8.dist-info/LICENSE
generalgui-2.0.8.dist-info/METADATA
generalgui-2.0.8.dist-info/WHEEL
generalgui-2.0.8.dist-info/top_level.txt
generalgui-2.0.8.dist-info/RECORD
