Metadata-Version: 2.1
Name: generalgui
Version: 2.0.8
Summary: Extends and simplifies tkinter functionality with built-in QoL improvements.
Home-page: https://github.com/ManderaGeneral/generalgui
Author: Rickard "Mandera" Abraham
Author-email: rickard.abraham@gmail.com
License: mit
Platform: UNKNOWN
Classifier: Topic :: Software Development :: User Interfaces
Classifier: Programming Language :: Python :: 3.8
Classifier: Programming Language :: Python :: 3.9
Classifier: License :: OSI Approved :: MIT License
Classifier: Operating System :: Microsoft :: Windows
Classifier: Operating System :: POSIX :: Linux
Requires-Python: >=3.8, <3.10
Requires-Dist: generalvector
Requires-Dist: generallibrary
Requires-Dist: pandas
Requires-Dist: numpy
